codeval/__init__.py
codeval/__main__.py
codeval/exec_template.txt
codeval/pyrustic_data/backstage/config/build.json
codeval/pyrustic_data/backstage/config/init.json
codeval/pyrustic_data/backstage/config/release.json
codeval/pyrustic_data/backstage/data/github_release_form.json
codeval/pyrustic_data/backstage/report/build_report.json
codeval/pyrustic_data/backstage/report/release_report.json
codeval/pyrustic_data/hubstore/img.json
codeval/pyrustic_data/hubstore/promotion.json
tests/__init__.py
codeval-0.0.2.dist-info/LICENSE
codeval-0.0.2.dist-info/METADATA
codeval-0.0.2.dist-info/WHEEL
codeval-0.0.2.dist-info/entry_points.txt
codeval-0.0.2.dist-info/top_level.txt
codeval-0.0.2.dist-info/RECORD
