Metadata-Version: 2.1
Name: codeval
Version: 0.0.2
Summary: Library to evaluate code submitted by user
Home-page: https://github.com/pyrustic/codeval
Author: Pyrustic Evangelist
Author-email: pyrustic@protonmail.com
Maintainer: Pyrustic Evangelist
Maintainer-email: pyrustic@protonmail.com
License: MIT
Keywords: codegame
Platform: UNKNOWN
Classifier: Programming Language :: Python :: 3
Classifier: License :: OSI Approved :: MIT License
Classifier: Operating System :: OS Independent
Requires-Python: >=3.5
